i_dunno/__init__.py
i_dunno/__main__.py
i_dunno/data.py
i_dunno-0.1.3.dist-info/LICENSE
i_dunno-0.1.3.dist-info/METADATA
i_dunno-0.1.3.dist-info/WHEEL
i_dunno-0.1.3.dist-info/entry_points.txt
i_dunno-0.1.3.dist-info/top_level.txt
i_dunno-0.1.3.dist-info/RECORD
