Metadata-Version: 2.1
Name: i-dunno
Version: 0.1.3
Summary: convert IPv6 or IPv4 addresses into RFC8771-compliant I-DUNNO representation
Home-page: https://github.com/lilyinstarlight/i-dunno
Author: Lily Foster
Author-email: lily@lily.flowers
License: MIT
Platform: UNKNOWN
Classifier: Development Status :: 4 - Beta
Classifier: Environment :: Console
Classifier: Intended Audience :: Developers
Classifier: License :: Freely Distributable
Classifier: License :: OSI Approved :: MIT License
Classifier: Operating System :: POSIX
Classifier: Operating System :: POSIX :: Linux
Classifier: Operating System :: MacOS :: MacOS X
Classifier: Programming Language :: Python
Classifier: Programming Language :: Python :: 3
Classifier: Topic :: Artistic Software
Classifier: Topic :: Software Development :: Libraries
Classifier: Topic :: Software Development :: Libraries :: Python Modules
Classifier: Topic :: Software Development :: Localization
Classifier: Topic :: Utilities
